<?xml version="1.0" encoding="utf-8" ?>
<dwsync>
<file name="forest.jpg" server="C:/xampp/htdocs/Web2/" local="132519979166727257" remote="132519979160000000" Dst="1" />
<file name="H logo.png" server="C:/xampp/htdocs/Web2/" local="132521817082859543" remote="132521817080000000" Dst="1" />
<file name="rossdraws.jpg" server="C:/xampp/htdocs/Web2/" local="132519650796275401" remote="132519650790000000" Dst="1" />
<file name="kuvshinov.jpg" server="C:/xampp/htdocs/Web2/" local="132522282491807230" remote="132522282490000000" Dst="1" />
<file name="wlop lion.jpg" server="C:/xampp/htdocs/Web2/" local="132522281336873821" remote="132522281330000000" Dst="1" />
<file name="ganev.png" server="C:/xampp/htdocs/Web2/" local="132522283134265043" remote="132522283130000000" Dst="1" />
<file name="wlop2.jpg" server="C:/xampp/htdocs/Web2/" local="132522282914026492" remote="132522282910000000" Dst="1" />
<file name="rossdraws2.jpg" server="C:/xampp/htdocs/Web2/" local="132522283565407323" remote="132522283560000000" Dst="1" />
<file name="beautiful.jpg" server="C:/xampp/htdocs/Web2/" local="132517055583249973" remote="132517055580000000" Dst="1" />
<file name="zhong.jpg" server="C:/xampp/htdocs/Web2/" local="132522284472666061" remote="132522284470000000" Dst="1" />
</dwsync>